README.rst
setup.cfg
setup.py
listools/__init__.py
listools.egg-info/PKG-INFO
listools.egg-info/SOURCES.txt
listools.egg-info/dependency_links.txt
listools.egg-info/top_level.txt
listools/flatools/__init__.py
listools/flatools/flatten.py
listools/flatools/flatten_choice.py
listools/flatools/flatten_index.py
listools/flatools/flatten_join.py
listools/flatools/flatten_len.py
listools/flatools/flatten_max.py
listools/flatools/flatten_min.py
listools/flatools/flatten_mixed_type.py
listools/flatools/flatten_reverse.py
listools/flatools/flatten_single_type.py
listools/flatools/flatten_sorted.py
listools/flatools/flatten_sum.py
listools/flatools/flatten_zip_cycle.py
listools/flatools/pflatten.py
listools/iterz/__init__.py
listools/iterz/cycle_until_index.py
listools/iterz/inf_cycle.py
listools/iterz/iter_mask.py
listools/iterz/ncycle.py
listools/iterz/zip_cycle.py
listools/iterz/zip_inf_cycle.py
listools/iterz/zip_longest.py
listools/iterz/zip_syzygy.py
listools/listutils/__init__.py
listools/listutils/list_gcd.py
listools/listutils/list_lcm.py
listools/listutils/list_mask.py
listools/listutils/list_mask_cycle.py
listools/listutils/period_len.py
listools/listutils/shuffle.py
listools/llogic/__init__.py
listools/llogic/difference.py
listools/llogic/intersection.py
listools/llogic/is_ascending.py
listools/llogic/is_contained.py
listools/llogic/is_descending.py
listools/llogic/mixed_type.py
listools/llogic/single_type.py
listools/llogic/symmetric_difference.py
listools/llogic/union.py
tests/__init__.py
tests/test_flatools.py
tests/test_iterz.py
tests/test_listutils.py
tests/test_llogic.py